browser_use_starter/__init__.py
browser_use_starter/agent.py
browser_use_starter/config.py
browser_use_starter/setup_browsers.py
browser_use_starter/utils.py
browser_use_starter/verify_setup.py
browser_use_starter/tests/__init__.py
browser_use_starter/tests/test_browser.py
browser_use_starter/tests/test_config.py
browser_use_cli-0.1.0.dist-info/METADATA
browser_use_cli-0.1.0.dist-info/WHEEL
browser_use_cli-0.1.0.dist-info/entry_points.txt
browser_use_cli-0.1.0.dist-info/top_level.txt
browser_use_cli-0.1.0.dist-info/RECORD
