Metadata-Version: 2.2
Name: browser-use-cli
Version: 0.1.0
Summary: CLI tool for browser automation tasks
Requires-Python: >=3.11
Requires-Dist: browser-use>=0.1.37
Requires-Dist: langchain-google-genai>=2.0.8
Requires-Dist: python-dotenv>=1.0.0
Requires-Dist: playwright>=1.40.0
Requires-Dist: rich>=13.9.0
Provides-Extra: dev
Requires-Dist: black>=23.0.0; extra == "dev"
Requires-Dist: isort>=5.12.0; extra == "dev"
Requires-Dist: flake8>=6.0.0; extra == "dev"
Requires-Dist: pytest>=7.0.0; extra == "dev"
Requires-Dist: pre-commit>=3.0.0; extra == "dev"
